deplyai/__init__.py
deplyai/_interfaces.py
deplyai/id_generator.py
deplyai/_schema/__init__.py
deplyai/_schema/cli.py
deplyai/_schema/schema.py
deplyai/_utils/__init__.py
deplyai/_utils/graph.py
deplyai/_utils/print.py
deplyai/blocks/__init__.py
deplyai/blocks/definition.py
deplyai/config/__init__.py
deplyai/config/_parser.py
deplyai/connector/__init__.py
deplyai/connector/_connector.py
deplyai/parser/__init__.py
deplyai/parser/eval.py
deplyai/runner/__init__.py
deplyai-0.2.4.dist-info/LICENSE
deplyai-0.2.4.dist-info/METADATA
deplyai-0.2.4.dist-info/WHEEL
deplyai-0.2.4.dist-info/top_level.txt
deplyai-0.2.4.dist-info/RECORD
